dell_runtime/__init__.py
dell_runtime/aerjob.py
dell_runtime/backend_provider.py
dell_runtime/dell_runtime_provider.py
dell_runtime/emulation_executor.py
dell_runtime/emulator_backend.py
dell_runtime/emulator_job.py
dell_runtime/emulator_runtime_job.py
dell_runtime/emulator_runtime_service.py
dell_runtime/local_sub_provider.py
dell_runtime/local_user_messenger.py
dell_runtime/remote_runtime_service.py
qiskit_dell_runtime-0.1.5.dist-info/LICENSE
qiskit_dell_runtime-0.1.5.dist-info/METADATA
qiskit_dell_runtime-0.1.5.dist-info/WHEEL
qiskit_dell_runtime-0.1.5.dist-info/top_level.txt
qiskit_dell_runtime-0.1.5.dist-info/RECORD
