Metadata-Version: 2.1
Name: qiskit-dell-runtime
Version: 0.1.5
Summary: Dell provider for Qiskit Runtime backends
Author-email: Dell Technologies <ben_santaus@dell.com>
License: Apache License
Project-URL: Homepage, https://github.com/Qiskit-Partners/qiskit-dell-runtime/
Classifier: Environment :: Console
Classifier: License :: OSI Approved :: Apache Software License
Classifier: Intended Audience :: Developers
Classifier: Intended Audience :: Science/Research
Classifier: Operating System :: Microsoft :: Windows
Classifier: Operating System :: MacOS
Classifier: Operating System :: POSIX :: Linux
Classifier: Programming Language :: Python :: 3 :: Only
Classifier: Programming Language :: Python :: 3.6
Classifier: Topic :: Scientific/Engineering
Requires-Python: >=3.8
License-File: LICENSE
Requires-Dist: qiskit >=0.41.0
Requires-Dist: qiskit-aer >=0.13.1
Requires-Dist: qiskit-ibmq-provider >=0.13.0
